pyglet_ffmpeg/__init__.py
pyglet_ffmpeg/loader.py
pyglet_ffmpeg/RPi/libavcodec.so.58.21.105
pyglet_ffmpeg/RPi/libavfilter.so.7.25.100
pyglet_ffmpeg/RPi/libavformat.so.58.17.101
pyglet_ffmpeg/RPi/libavutil.so.56.18.102
pyglet_ffmpeg/RPi/libswresample.so.3.2.100
pyglet_ffmpeg/RPi/libswscale.so.5.2.100
pyglet_ffmpeg-0.1.5.dist-info/METADATA
pyglet_ffmpeg-0.1.5.dist-info/RECORD
pyglet_ffmpeg-0.1.5.dist-info/WHEEL
pyglet_ffmpeg-0.1.5.dist-info/top_level.txt
